{ "height":15,
 "infinite":false,
 "layers":[
        {
         "data":[1200, 1200, 1202, 1201, 1203, 1202, 1202, 1201, 1201, 1200, 1202, 1202, 1200, 1202, 1203, 1202, 1200, 1200, 1200, 1202, 1202, 1202, 1203, 1201, 1203, 1202, 1201, 1203, 1200, 1202, 1202, 1203, 1203, 1203, 1200, 1202, 1201, 1201, 1201, 1200, 1200, 1201, 1201, 1202, 1203, 1203, 1201, 1203, 1201, 1201, 1202, 1201, 1201, 1202, 1202, 1203, 1203, 1200, 1201, 1201, 1201, 1200, 1201, 1202, 1202, 1203, 1202, 1200, 1201, 1201, 1202, 1203, 1202, 1203, 1200, 1202, 1200, 1203, 1201, 1202, 1203, 1200, 1201, 1201, 1201, 1200, 1203, 1202, 1203, 1200, 1201, 1200, 1200, 1202, 1202, 1200, 1202, 1203, 1203, 1200, 1202, 1200, 847, 852, 848, 852, 853, 1202, 1203, 1203, 1202, 1202, 1202, 1202, 1200, 1202, 1200, 1200, 1200, 1201, 1202, 849, 1070, 1070, 1070, 851, 1200, 1201, 1202, 1200, 1202, 1201, 1201, 1200, 1203, 1201, 1201, 1203, 1203, 1200, 847, 1070, 1070, 1070, 852, 1202, 1201, 1200, 1203, 1200, 1200, 1200, 1201, 1203, 1203, 1202, 1203, 1203, 1201, 851, 1070, 1070, 1070, 849, 1203, 1203, 1202, 1200, 1200, 1200, 1201, 1200, 1202, 1203, 1202, 1203, 1200, 1200, 849, 850, 849, 847, 850, 1201, 1203, 1200, 1201, 1200, 1200, 1201, 1203, 1202, 1202, 1200, 1200, 1201, 1203, 1200, 1202, 1200, 1202, 1203, 1202, 1201, 1200, 1201, 1202, 1203, 1200, 1201, 1203, 1203, 1202, 1200, 1201, 1202, 1201, 1200, 1201, 1202, 1201, 1203, 1203, 1200, 1203, 1202, 1203, 1200, 1202, 1203, 1203, 1203, 1202, 1202, 1202, 1200, 1200, 1202, 1200, 1202, 1201, 1202, 1200, 1202, 1203, 1200, 1203, 1202, 1203, 1201, 1202, 1200, 1202, 1202, 1201, 1201, 1201, 1201, 1203, 1201, 1203, 1201, 1201, 1201, 1200, 1201, 1203, 1200, 1203, 1201, 1203, 1203, 1203, 1200, 1200, 1201, 1202, 1202, 1200, 1201, 1202, 1203, 1201, 1201, 1201],
         "height":15,
         "id":10,
         "name":"background",
         "opacity":1,
         "type":"tilelayer",
         "visible":true,
         "width":19,
         "x":0,
         "y":0
        }, 
        {
         "data":[798, 797, 799, 799, 803, 800, 802, 800, 798, 798, 802, 804, 796, 802, 801, 800, 798, 800, 797, 798, 0, 0, 0, 797, 0, 0, 0, 0, 0, 0, 0, 0, 802, 0, 0, 0, 0, 797, 804, 0, 800, 0, 797, 0, 802, 0, 797, 804, 802, 803, 0, 799, 0, 801, 799, 796, 804, 796, 0, 0, 0, 802, 0, 796, 0, 0, 0, 796, 0, 0, 0, 0, 0, 0, 0, 796, 802, 0, 803, 0, 0, 0, 800, 802, 797, 0, 798, 0, 800, 797, 800, 799, 799, 0, 797, 800, 0, 798, 0, 804, 0, 0, 1174, 1174, 1171, 1172, 1172, 0, 0, 0, 799, 0, 0, 799, 798, 0, 799, 801, 797, 798, 796, 1172, 0, 0, 0, 1173, 0, 801, 0, 798, 0, 797, 800, 800, 0, 0, 0, 0, 0, 0, 1173, 0, 0, 0, 1171, 0, 802, 0, 0, 0, 0, 796, 800, 800, 800, 800, 0, 800, 0, 1174, 0, 0, 0, 1174, 0, 804, 796, 800, 800, 0, 801, 800, 0, 0, 800, 0, 801, 0, 1172, 1174, 0, 1174, 1172, 0, 0, 0, 0, 802, 0, 799, 797, 798, 0, 796, 0, 798, 803, 0, 0, 0, 0, 0, 802, 796, 801, 803, 802, 0, 796, 802, 0, 0, 803, 0, 0, 0, 0, 801, 0, 798, 0, 801, 0, 0, 0, 798, 0, 803, 804, 0, 801, 798, 803, 802, 801, 801, 797, 801, 800, 798, 804, 0, 798, 0, 800, 0, 800, 799, 0, 0, 0, 0, 0, 0, 0, 0, 0, 0, 0, 0, 0, 799, 0, 0, 0, 804, 802, 804, 799, 802, 798, 796, 804, 799, 798, 798, 796, 796, 797, 800, 804, 804, 798, 803, 802],
         "height":15,
         "id":11,
         "name":"walls",
         "opacity":1,
         "type":"tilelayer",
         "visible":true,
         "width":19,
         "x":0,
         "y":0
        }, 
        {
         "draworder":"topdown",
         "id":7,
         "name":"objects",
         "objects":[
                {
                 "gid":1291,
                 "height":32,
                 "id":25,
                 "name":"win",
                 "properties":[
                        {
                         "name":"description",
                         "type":"string",
                         "value":"Did you find the light?"
                        }, 
                        {
                         "name":"subject",
                         "type":"string",
                         "value":"you found the item"
                        }, 
                        {
                         "name":"title",
                         "type":"string",
                         "value":"You win!"
                        }],
                 "rotation":0,
                 "type":"win",
                 "visible":true,
                 "width":32,
                 "x":288,
                 "y":256
                }, 
                {
                 "gid":2749,
                 "height":32,
                 "id":44,
                 "name":"revealmap",
                 "rotation":0,
                 "type":"showmap",
                 "visible":false,
                 "width":32,
                 "x":480,
                 "y":320
                }, 
                {
                 "gid":1,
                 "height":32,
                 "id":45,
                 "name":"reveal",
                 "properties":[
                        {
                         "name":"object",
                         "type":"int",
                         "value":44
                        }],
                 "rotation":0,
                 "type":"show",
                 "visible":true,
                 "width":32,
                 "x":448,
                 "y":320
                }],
         "opacity":1,
         "type":"objectgroup",
         "visible":true,
         "x":0,
         "y":0
        }],
 "nextlayerid":12,
 "nextobjectid":46,
 "orientation":"orthogonal",
 "properties":[
        {
         "name":"darkness",
         "type":"bool",
         "value":true
        }, 
        {
         "name":"herosprite",
         "type":"int",
         "value":2909
        }, 
        {
         "name":"startx",
         "type":"int",
         "value":17
        }, 
        {
         "name":"starty",
         "type":"int",
         "value":13
        }],
 "renderorder":"left-up",
 "tiledversion":"1.2.0",
 "tileheight":32,
 "tilesets":[
        {
         "columns":64,
         "firstgid":1,
         "image":"DungeonCrawl_ProjectUtumnoTileset.png",
         "imageheight":1536,
         "imagewidth":2048,
         "margin":0,
         "name":"Tiles",
         "spacing":0,
         "tilecount":3072,
         "tileheight":32,
         "tilewidth":32
        }],
 "tilewidth":32,
 "type":"map",
 "version":1.2,
 "width":19
}